gatingDesign/__init__.py
gatingDesign/gatingDesign.py
gatingDesign/gatingDesignGUI.py
gatingDesign/images/gatingSystem.jpg
gatingDesign/images/SlimGating.jpg
gatingDesign/saveFile.py
gatingdesign-1.1.1.dist-info/METADATA
gatingdesign-1.1.1.dist-info/WHEEL
gatingdesign-1.1.1.dist-info/RECORD
